{
  "hash": "bcc6e3a227d2ac475aaf491a829bbdf3",
  "result": {
    "markdown": "---\ntitle: \"Challenge 1 \"\nauthor: \"Xiaoyan Hu\"\ndescription: \"Reading in data and creating a post\"\ndate: \"09/16/2022??\"\nformat:\n  html:\n    toc: true\n    code-fold: true\n    code-copy: true\n    code-tools: true\ncategories:\n  - challenge_1\n  - railroads\n  - faostat\n  - wildbirds.\n---\n\n::: {.cell}\n\n```{.r .cell-code}\nlibrary(tidyverse)\n\nknitr::opts_chunk$set(echo = TRUE, warning=FALSE, message=FALSE)\n```\n:::\n\n\n## Challenge Overview\n\nToday's challenge is to\n\n1)  read in a dataset, and\n\n2)  describe the dataset using both words and any supporting information (e.g., tables, etc)\n\n## Read in the Data\n\nRead in one (or more) of the following data sets, using the correct R package and command.\n\n-   railroad_2012_clean_county.csv ⭐\n-   birds.csv ⭐⭐\n-   FAOstat\\*.csv ⭐⭐\n-   wild_bird_data.xlsx ⭐⭐⭐\n-   StateCounty2012.xls ⭐⭐⭐⭐\n\nFind the `_data` folder, located inside the `posts` folder. Then you can read in the data, using either one of the `readr` standard tidy read commands, or a specialized package such as `readxl`\n\n\n::: {.cell}\n\n```{.r .cell-code}\nsetwd(\"/Users/cassie199/Desktop/22fall/DACSS601/601_Fall_2022/posts/_data\")\ndata1 <- read.csv(\"/Users/cassie199/Desktop/22fall/DACSS601/601_Fall_2022/posts/_data/railroad_2012_clean_county.csv\")\nhead(data1)\n```\n\n::: {.cell-output .cell-output-stdout}\n```\n  state               county total_employees\n1    AE                  APO               2\n2    AK            ANCHORAGE               7\n3    AK FAIRBANKS NORTH STAR               2\n4    AK               JUNEAU               3\n5    AK    MATANUSKA-SUSITNA               2\n6    AK                SITKA               1\n```\n:::\n\n```{.r .cell-code}\ndata2<- read.csv(\"/Users/cassie199/Desktop/22fall/DACSS601/601_Fall_2022/posts/_data/birds.csv\")\n```\n:::\n\n\nAdd any comments or documentation as needed. More challenging data sets may require additional code chunks and documentation.\n\n## Describe the data\n\nUsing a combination of words and results of R commands, can you provide a high level description of the data? Describe as efficiently as possible where/how the data was (likely) gathered, indicate the cases and variables (both the interpretation and any details you deem useful to the reader to fully understand your chosen data).\n\n1. data railroad shows a statistic of railroad with state, counties and total employees\n the table contains 2930 obervations and 3 varibales\n2.birds file described with informations of birds with their areas, value, items and so on. This file contains 30977 observations and 14 variables\n\n\n\n::: {.cell}\n\n```{.r .cell-code}\ndim(data1)\n```\n\n::: {.cell-output .cell-output-stdout}\n```\n[1] 2930    3\n```\n:::\n\n```{.r .cell-code}\ncolnames(data1)\n```\n\n::: {.cell-output .cell-output-stdout}\n```\n[1] \"state\"           \"county\"          \"total_employees\"\n```\n:::\n\n```{.r .cell-code}\nhead(data1)\n```\n\n::: {.cell-output .cell-output-stdout}\n```\n  state               county total_employees\n1    AE                  APO               2\n2    AK            ANCHORAGE               7\n3    AK FAIRBANKS NORTH STAR               2\n4    AK               JUNEAU               3\n5    AK    MATANUSKA-SUSITNA               2\n6    AK                SITKA               1\n```\n:::\n\n```{.r .cell-code}\n#|birds file described with informations of birds with their areas, value, \n#|the data contains 30977 obersvations and 14 variables\n\nhead(data2)\n```\n\n::: {.cell-output .cell-output-stdout}\n```\n  Domain.Code       Domain Area.Code        Area Element.Code Element Item.Code\n1          QA Live Animals         2 Afghanistan         5112  Stocks      1057\n2          QA Live Animals         2 Afghanistan         5112  Stocks      1057\n3          QA Live Animals         2 Afghanistan         5112  Stocks      1057\n4          QA Live Animals         2 Afghanistan         5112  Stocks      1057\n5          QA Live Animals         2 Afghanistan         5112  Stocks      1057\n6          QA Live Animals         2 Afghanistan         5112  Stocks      1057\n      Item Year.Code Year      Unit Value Flag Flag.Description\n1 Chickens      1961 1961 1000 Head  4700    F     FAO estimate\n2 Chickens      1962 1962 1000 Head  4900    F     FAO estimate\n3 Chickens      1963 1963 1000 Head  5000    F     FAO estimate\n4 Chickens      1964 1964 1000 Head  5300    F     FAO estimate\n5 Chickens      1965 1965 1000 Head  5500    F     FAO estimate\n6 Chickens      1966 1966 1000 Head  5800    F     FAO estimate\n```\n:::\n\n```{.r .cell-code}\ncolnames(data2)\n```\n\n::: {.cell-output .cell-output-stdout}\n```\n [1] \"Domain.Code\"      \"Domain\"           \"Area.Code\"        \"Area\"            \n [5] \"Element.Code\"     \"Element\"          \"Item.Code\"        \"Item\"            \n [9] \"Year.Code\"        \"Year\"             \"Unit\"             \"Value\"           \n[13] \"Flag\"             \"Flag.Description\"\n```\n:::\n\n```{.r .cell-code}\ndim(data2)\n```\n\n::: {.cell-output .cell-output-stdout}\n```\n[1] 30977    14\n```\n:::\n:::\n",
    "supporting": [],
    "filters": [
      "rmarkdown/pagebreak.lua"
    ],
    "includes": {},
    "engineDependencies": {},
    "preserve": {},
    "postProcess": true
  }
}